Metadata-Version: 1.1
Name: pyintralinks
Version: 0.1.1
Summary: A python client for intralinks api.
Home-page: https://github.com/delciotorres/pyintralinks
Author: Delcio Torres
Author-email: delciotorres@gmail.com
License: MIT
Keywords: intralinks,api
Platform: UNKNOWN
Classifier: Development Status :: 1 - Planning
Classifier: Intended Audience :: Developers
Classifier: License :: OSI Approved :: MIT License
Classifier: Operating System :: OS Independent
Classifier: Programming Language :: Python
Classifier: Programming Language :: Python :: 3.6
Classifier: Topic :: Communications :: File Sharing
Classifier: Topic :: Software Development :: Libraries :: Python Modules
